reflect/__init__.py
reflect/database.py
reflectdb-0.2.dist-info/LICENSE
reflectdb-0.2.dist-info/METADATA
reflectdb-0.2.dist-info/WHEEL
reflectdb-0.2.dist-info/top_level.txt
reflectdb-0.2.dist-info/RECORD
