Metadata-Version: 2.1
Name: reflectdb
Version: 0.2
Summary: Low Ram Focused Database System in Python
Home-page: https://github.com/Ow1e/ReflectDB
Author: Owen Shaule
Author-email: ow1e3@protonmail.com
License: UNKNOWN
Keywords: python,database
Platform: UNKNOWN
License-File: LICENSE
Requires-Dist: asyncio
